ddp_asyncio/__init__.py
ddp_asyncio/collection.py
ddp_asyncio/ddp_asyncio.py
ddp_asyncio/ddpclient.py
ddp_asyncio/dotable.py
ddp_asyncio/exceptions.py
ddp_asyncio/methodcall.py
ddp_asyncio/subscription.py
ddp_asyncio/extras/__init__.py
ddp_asyncio/extras/meteor_files_uploader.py
ddp_asyncio-0.3.0.dist-info/METADATA
ddp_asyncio-0.3.0.dist-info/RECORD
ddp_asyncio-0.3.0.dist-info/WHEEL
ddp_asyncio-0.3.0.dist-info/top_level.txt
