Metadata-Version: 2.1
Name: ddp-asyncio
Version: 0.3.0
Summary: Asynchronous DDP library
Home-page: https://github.com/hunternet93/ddp_asyncio
Author: Isaac Smith
Author-email: isaac@isrv.pw
License: MIT
Download-URL: https://github.com/hunternet93/ddp_asyncio/releases/download/0.2.0/ddp_asyncio-0.2.0.tar.gz
Keywords: ddp meteor
Platform: UNKNOWN
Classifier: Development Status :: 4 - Beta
Classifier: Intended Audience :: Developers
Classifier: License :: OSI Approved :: MIT License
Classifier: Operating System :: OS Independent
Classifier: Programming Language :: Python :: 3.5
Classifier: Programming Language :: Python :: 3.6
Classifier: Programming Language :: Python :: 3.7
Classifier: Framework :: AsyncIO
Requires-Dist: websockets
Requires-Dist: ejson
